{
  "position": "Center",
  "height": 83,
  "wingspan": 84,
  "weight": 220,
  "close_shot": 99,
  "driving_layup": 94,
  "driving_dunk": 88,
  "standing_dunk": 97,
  "post_control": 99,
  "mid_range_shot": 92,
  "three_point_shot": 89,
  "free_throw": 93,
  "pass_accuracy": 99,
  "ball_handle": 74,
  "speed_with_ball": 66,
  "interior_defense": 91,
  "perimeter_defense": 76,
  "steal": 69,
  "block": 93,
  "offensive_rebound": 83,
  "defensive_rebound": 84,
  "speed": 78,
  "strength": 85,
  "vertical": 89,
  "agility": 70
}